logperformance/__init__.py
logperformance/logger.py
logperformance-1.0.1.dist-info/METADATA
logperformance-1.0.1.dist-info/WHEEL
logperformance-1.0.1.dist-info/RECORD
