Metadata-Version: 2.3
Name: logperformance
Version: 1.0.1
Summary: Classe que implementa um logger com funções de log performance, log error, log warning, log info, log debug, log critical, log alert, log emergency, log warning, log error, log critical, log alert, log emergency
Author: greghono@gmail.com
Requires-Python: >=3.11
Classifier: Programming Language :: Python :: 3
Classifier: Programming Language :: Python :: 3.11
Classifier: Programming Language :: Python :: 3.12
Classifier: Programming Language :: Python :: 3.13
Provides-Extra: dev
Requires-Dist: colorlog (>=6.9.0,<7.0.0)
Requires-Dist: pytest (>=8.3.5,<9.0.0) ; extra == "dev"
Requires-Dist: setuptools (>=80.1.0,<81.0.0) ; extra == "dev"
Requires-Dist: twine (>=6.1.0,<7.0.0) ; extra == "dev"
